modbus_gui_app/__init__.py
modbus_gui_app/db_handler.py
modbus_gui_app/main.py
modbus_gui_app/communication/__init__.py
modbus_gui_app/communication/modbus_connection.py
modbus_gui_app/communication/request_serializer.py
modbus_gui_app/communication/response_deserializer.py
modbus_gui_app/database/db_handler.py
modbus_gui_app/gui/__init__.py
modbus_gui_app/gui/current_state_window.py
modbus_gui_app/gui/error_window.py
modbus_gui_app/gui/gui_left_side.py
modbus_gui_app/gui/gui_middle.py
modbus_gui_app/gui/gui_right_side.py
modbus_gui_app/gui/history_window.py
modbus_gui_app/gui/request_validation.py
modbus_gui_app/gui/window.py
modbus_gui_app/state/__init__.py
modbus_gui_app/state/data_structures.py
modbus_gui_app/state/live_update.py
modbus_gui_app/state/state_manager.py
test/test_communication/test_modbus_connection.py
test/test_communication/test_request_serializer.py
test/test_communication/test_response_deserializer.py
test/test_database/test_db_read.py
test/test_database/test_db_write.py
test/test_state/test_data_structures.py
test/test_state/test_live_update.py
test/test_state/test_state_manager.py
ModbusGuiApp-1.1.dist-info/METADATA
ModbusGuiApp-1.1.dist-info/WHEEL
ModbusGuiApp-1.1.dist-info/entry_points.txt
ModbusGuiApp-1.1.dist-info/license.md
ModbusGuiApp-1.1.dist-info/top_level.txt
ModbusGuiApp-1.1.dist-info/RECORD
