Metadata-Version: 2.1
Name: ModbusGuiApp
Version: 1.1
Summary: ModbusGuiApplication.
Home-page: UNKNOWN
Author: Ivan Cindric
Author-email: ivan.cindric95@example.com
License: UNKNOWN
Platform: UNKNOWN
Requires-Python: >=3.6
Requires-Dist: aiohttp (~=3.6.2)
Requires-Dist: pytest (~=6.0.1)
Requires-Dist: PySide2 (~=5.15.0)
Requires-Dist: setuptools (~=49.6.0)
